dataknobs_data/__init__.py
dataknobs_data/database.py
dataknobs_data/database_utils.py
dataknobs_data/exceptions.py
dataknobs_data/factory.py
dataknobs_data/fields.py
dataknobs_data/py.typed
dataknobs_data/query.py
dataknobs_data/query_logic.py
dataknobs_data/records.py
dataknobs_data/schema.py
dataknobs_data/streaming.py
dataknobs_data/backends/__init__.py
dataknobs_data/backends/duckdb.py
dataknobs_data/backends/elasticsearch.py
dataknobs_data/backends/elasticsearch_async.py
dataknobs_data/backends/elasticsearch_mixins.py
dataknobs_data/backends/file.py
dataknobs_data/backends/memory.py
dataknobs_data/backends/postgres.py
dataknobs_data/backends/postgres_mixins.py
dataknobs_data/backends/postgres_vector.py
dataknobs_data/backends/s3.py
dataknobs_data/backends/s3_async.py
dataknobs_data/backends/sql_base.py
dataknobs_data/backends/sqlite.py
dataknobs_data/backends/sqlite_async.py
dataknobs_data/backends/sqlite_mixins.py
dataknobs_data/backends/vector_config_mixin.py
dataknobs_data/migration/__init__.py
dataknobs_data/migration/factory.py
dataknobs_data/migration/migration.py
dataknobs_data/migration/migrator.py
dataknobs_data/migration/operations.py
dataknobs_data/migration/progress.py
dataknobs_data/migration/transformer.py
dataknobs_data/pandas/__init__.py
dataknobs_data/pandas/batch_ops.py
dataknobs_data/pandas/converter.py
dataknobs_data/pandas/metadata.py
dataknobs_data/pandas/type_mapper.py
dataknobs_data/pooling/__init__.py
dataknobs_data/pooling/base.py
dataknobs_data/pooling/elasticsearch.py
dataknobs_data/pooling/postgres.py
dataknobs_data/pooling/s3.py
dataknobs_data/validation/__init__.py
dataknobs_data/validation/coercer.py
dataknobs_data/validation/constraints.py
dataknobs_data/validation/factory.py
dataknobs_data/validation/result.py
dataknobs_data/validation/schema.py
dataknobs_data/vector/__init__.py
dataknobs_data/vector/benchmarks.py
dataknobs_data/vector/bulk_embed_mixin.py
dataknobs_data/vector/elasticsearch_utils.py
dataknobs_data-0.4.5.dist-info/METADATA
dataknobs_data-0.4.5.dist-info/WHEEL
dataknobs_data-0.4.5.dist-info/RECORD
