Metadata-Version: 2.4
Name: dataknobs-data
Version: 0.4.5
Summary: Unified data abstraction layer for consistent database operations across multiple storage technologies
Project-URL: Homepage, https://github.com/dataknobs/dataknobs
Project-URL: Bug Tracker, https://github.com/dataknobs/dataknobs/issues
Project-URL: Documentation, https://dataknobs.readthedocs.io
Author-email: DataKnobs Team <team@dataknobs.com>
Keywords: abstraction,data,database,records,storage
Classifier: Development Status :: 3 - Alpha
Classifier: Intended Audience :: Developers
Classifier: Programming Language :: Python :: 3
Classifier: Programming Language :: Python :: 3.10
Classifier: Programming Language :: Python :: 3.11
Classifier: Programming Language :: Python :: 3.12
Requires-Python: >=3.10
Requires-Dist: aiofiles>=23.0.0
Requires-Dist: boto3>=1.38.27
Requires-Dist: dataknobs-common>=1.0.1
Requires-Dist: dataknobs-config>=0.1.0
Requires-Dist: dataknobs-utils>=0.1.0
Requires-Dist: moto>=5.1.10
Requires-Dist: numpy>=1.24.0
Requires-Dist: pandas>=2.0.0
Requires-Dist: pydantic>=2.0.0
Provides-Extra: all
Requires-Dist: aioboto3>=12.0.0; extra == 'all'
Requires-Dist: aiosqlite>=0.19.0; extra == 'all'
Requires-Dist: asyncpg>=0.29.0; extra == 'all'
Requires-Dist: boto3>=1.26.0; extra == 'all'
Requires-Dist: chromadb>=0.4.0; extra == 'all'
Requires-Dist: duckdb>=0.9.0; extra == 'all'
Requires-Dist: elasticsearch[async]<9.0.0,>=8.0.0; extra == 'all'
Requires-Dist: faiss-cpu>=1.7.4; extra == 'all'
Requires-Dist: pgvector>=0.2.0; extra == 'all'
Requires-Dist: psycopg2>=2.9.0; extra == 'all'
Requires-Dist: pyarrow>=14.0.0; extra == 'all'
Requires-Dist: sqlalchemy>=2.0.0; extra == 'all'
Provides-Extra: dev
Requires-Dist: black>=24.0.0; extra == 'dev'
Requires-Dist: moto>=4.2.0; extra == 'dev'
Requires-Dist: mypy>=1.0.0; extra == 'dev'
Requires-Dist: pytest-asyncio>=0.21.0; extra == 'dev'
Requires-Dist: pytest-cov>=4.0.0; extra == 'dev'
Requires-Dist: pytest-mock>=3.11.0; extra == 'dev'
Requires-Dist: pytest>=8.0.0; extra == 'dev'
Requires-Dist: ruff>=0.1.0; extra == 'dev'
Requires-Dist: testcontainers>=3.7.0; extra == 'dev'
Provides-Extra: duckdb
Requires-Dist: duckdb>=0.9.0; extra == 'duckdb'
Provides-Extra: elasticsearch
Requires-Dist: elasticsearch[async]<9.0.0,>=8.0.0; extra == 'elasticsearch'
Provides-Extra: parquet
Requires-Dist: pyarrow>=14.0.0; extra == 'parquet'
Provides-Extra: postgres
Requires-Dist: asyncpg>=0.29.0; extra == 'postgres'
Requires-Dist: psycopg2>=2.9.0; extra == 'postgres'
Requires-Dist: sqlalchemy>=2.0.0; extra == 'postgres'
Provides-Extra: s3
Requires-Dist: aioboto3>=12.0.0; extra == 's3'
Requires-Dist: boto3>=1.26.0; extra == 's3'
Provides-Extra: sqlite
Requires-Dist: aiosqlite>=0.19.0; extra == 'sqlite'
Provides-Extra: vector
Requires-Dist: asyncpg>=0.29.0; extra == 'vector'
Requires-Dist: chromadb>=0.4.0; extra == 'vector'
Requires-Dist: faiss-cpu>=1.7.4; extra == 'vector'
Requires-Dist: pgvector>=0.2.0; extra == 'vector'
